seeq/addons/clustering/__init__.py
seeq/addons/clustering/__main__.py
seeq/addons/clustering/_install_addon.py
seeq/addons/clustering/_notebook.ipynb
seeq/addons/clustering/_version.py
seeq/addons/clustering/_external_calc_override/__init__.py
seeq/addons/clustering/_external_calc_override/__main__.py
seeq/addons/clustering/_external_calc_override/_config.py
seeq/addons/clustering/_external_calc_override/override.py
seeq/addons/clustering/app/__init__.py
seeq/addons/clustering/app/clusterApp/__init__.py
seeq/addons/clustering/app/clusterApp/checksum.py
seeq/addons/clustering/app/clusterApp/main.py
seeq/addons/clustering/app/clusterApp/ui.py
seeq/addons/clustering/app/clusterApp/display/__init__.py
seeq/addons/clustering/app/clusterApp/display/main.py
seeq/addons/clustering/app/historicalBenchmarking/__init__.py
seeq/addons/clustering/app/historicalBenchmarking/cluster.py
seeq/addons/clustering/app/historicalBenchmarking/contour.py
seeq/addons/clustering/app/historicalBenchmarking/core.py
seeq/addons/clustering/app/seeqInterface/__init__.py
seeq/addons/clustering/app/seeqInterface/main.py
seeq/addons/clustering/config/__main__.py
seeq/addons/clustering/config/_config.py
seeq_clustering-0.2.2.dist-info/LICENSE
seeq_clustering-0.2.2.dist-info/METADATA
seeq_clustering-0.2.2.dist-info/NOTICE
seeq_clustering-0.2.2.dist-info/WHEEL
seeq_clustering-0.2.2.dist-info/top_level.txt
seeq_clustering-0.2.2.dist-info/RECORD
