Metadata-Version: 2.1
Name: seeq-clustering
Version: 0.2.2
Summary: Clustering of data in Seeq
Home-page: https://github.com/seeq12/seeq-clustering
Author: Eric Parsonnet
Author-email: e.parsonnet@berkeley.edu
License: Apache License 2.0
Platform: Linux
Platform: Windows
Classifier: Programming Language :: Python :: 3.7
Classifier: License :: OSI Approved :: Apache Software License
Classifier: Operating System :: OS Independent
Requires-Python: >=3.7
License-File: LICENSE
License-File: NOTICE
Requires-Dist: hdbscan (>=0.8.27)
Requires-Dist: bokeh (>=2.4.2)
Requires-Dist: numpy (>=1.22.0)
Requires-Dist: pandas (>=1.3.5)
